mag/__init__.py
mag/np/__init__.py
mag/np/arr.py
mag/np/files.py
mag/np/mat.py
mag/np/metrics.py
mag/np/prune.py
mag/py/__init__.py
mag/py/dict.py
mag/py/files.py
mag/py/json.py
mag/py/math.py
mag/py/os.py
mag/py/sets.py
mag/py/time.py
mag/skl/__init__.py
mag/skl/alignment.py
mag/skl/iou.py
mag/skl/mask_accuracy.py
mag/skl/segmentation.py
mag/sp/__init__.py
mag/tf/__init__.py
mag/tf/data.py
mag/tf/devices.py
mag/tf/arch/__init__.py
mag/tf/arch/conv.py
mag/tf/arch/losses.py
mag/tf/arch/ademxapp1d/__init__.py
mag/tf/arch/ademxapp1d/block.py
mag/tf/arch/ademxapp1d/branch.py
mag/tf/arch/ademxapp1d/chain.py
mag/tf/arch/ademxapp1d/tower.py
mag/tf/metrics/MultiLabel.py
mag/tf/metrics/__init__.py
mag-0.0.37.dist-info/LICENSE
mag-0.0.37.dist-info/METADATA
mag-0.0.37.dist-info/WHEEL
mag-0.0.37.dist-info/top_level.txt
mag-0.0.37.dist-info/RECORD
