Metadata-Version: 2.1
Name: mag
Version: 0.0.37
Summary: mag of utilities
Home-page: https://gitlab.com/SumNeuron/mag
Author: Sumner Magruder
Author-email: sumner.magruder@zmnh.uni-hamburg.de
License: UNKNOWN
Platform: UNKNOWN
Classifier: Programming Language :: Python :: 3.5
Classifier: License :: OSI Approved :: MIT License
Classifier: Operating System :: OS Independent
